{
  "version": "1.0",
  "savedAt": "12.05.2026, 09:37",
  "savedAtISO": "2026-05-12T06:37:13.600Z",
  "hebrewYear": 5787,
  "events": [],
  "blockedDays": {},
  "customHolidays": {
    "2026-12-16": {
      "name": "מבחן תנופה בשפת אם לכיתות ד' (דוברי ערבית)",
      "type": "custom"
    },
    "2026-12-30": {
      "name": "מבחן תנופה בשפת אם לכיתות ד' (דוברי עברית ממלכתי וממד)",
      "type": "custom"
    },
    "2027-05-05": {
      "name": "מבחן תנופה באנגלית לכיתות ו'",
      "type": "custom"
    },
    "2027-05-18": {
      "name": "מבחן תנופה בתנך לכיתות ו'",
      "type": "custom"
    },
    "2027-05-26": {
      "name": "מבחן תנופה בעברית לדוברי ערבית לכיתות ו'",
      "type": "custom"
    },
    "2027-05-31": {
      "name": "מבחן תנופה במדע וטכנולוגיה לכיתות ו'",
      "type": "custom"
    },
    "2027-06-02": {
      "name": "מבחן תנופה למיומנויות המאה ה21 לכיתות ו'",
      "type": "custom"
    },
    "2027-06-08": {
      "name": "מבחן תנופה במתמטיקה לכיתות ו'",
      "type": "custom"
    }
  },
  "cancelledDates": {},
  "postponedDates": {},
  "cellNotes": {},
  "hiddenHolidays": {}
}